poe_shell/__init__.py
poe_shell/__main__.py
poe_shell/config.py
poe_shell/handlers/__init__.py
poe_shell/handlers/chat_handler.py
poe_shell/handlers/handler.py
poe_shell/handlers/one_off_handler.py
poe_shell/handlers/shell_handler.py
poe_shell/poe_client.py
poe_shell/roles.py
poe_shell/utils.py
poe_shell-0.1.7.dist-info/METADATA
poe_shell-0.1.7.dist-info/WHEEL
poe_shell-0.1.7.dist-info/entry_points.txt
poe_shell-0.1.7.dist-info/RECORD
