Metadata-Version: 2.1
Name: poe-shell
Version: 0.1.7
Summary: 
Author: Samson Hui
Author-email: hui.kawang@yahoo.com.hk
Requires-Python: >=3.11,<4.0
Classifier: Programming Language :: Python :: 3
Classifier: Programming Language :: Python :: 3.11
Requires-Dist: poe-api (>=0.4.6,<0.5.0)
Requires-Dist: typer[all] (>=0.9.0,<0.10.0)
